ws_upload_spdx/__init__.py
ws_upload_spdx/_version.py
ws_upload_spdx/conftest.py
ws_upload_spdx/upload_spdx.py
ws_upload_spdx-0.0.2.dist-info/LICENSE
ws_upload_spdx-0.0.2.dist-info/METADATA
ws_upload_spdx-0.0.2.dist-info/WHEEL
ws_upload_spdx-0.0.2.dist-info/entry_points.txt
ws_upload_spdx-0.0.2.dist-info/top_level.txt
ws_upload_spdx-0.0.2.dist-info/RECORD
