Metadata-Version: 2.1
Name: ws-upload-spdx
Version: 0.0.2
Summary: Preparation upload file for Mend UI
Home-page: https://github.com/whitesource-ps/ws-upload-spdx
Author: WhiteSource Professional Services
Author-email: ps@whitesourcesoftware.com
License: LICENSE.txt
Platform: UNKNOWN
Classifier: Programming Language :: Python :: 3.9
Classifier: Programming Language :: Python :: 3.10
Classifier: License :: OSI Approved :: Apache Software License
Classifier: Operating System :: OS Independent
Requires-Python: >=3.9
License-File: LICENSE
